tart/__init__.py
tart/imaging/.gitignore
tart/imaging/Makefile
tart/imaging/README.md
tart/imaging/__init__.py
tart/imaging/antenna_model.py
tart/imaging/calibration.py
tart/imaging/correlator.py
tart/imaging/elaz.py
tart/imaging/ephemerides_proxy.py
tart/imaging/ephemeris.py
tart/imaging/gps_satellite.py
tart/imaging/gps_time.py
tart/imaging/imaging.py
tart/imaging/location.py
tart/imaging/radio_source.py
tart/imaging/simulate_transit.py
tart/imaging/sp3_interpolator.py
tart/imaging/sun.py
tart/imaging/synthesis.py
tart/imaging/tart_util.py
tart/imaging/visibility.py
tart/imaging/test/.gitignore
tart/imaging/test/__init__.py
tart/imaging/test/all.py
tart/imaging/test/test_antenna_model.py
tart/imaging/test/test_correlator.py
tart/imaging/test/test_elaz.py
tart/imaging/test/test_ephemerides_proxy.py
tart/imaging/test/test_ephemeris.py
tart/imaging/test/test_gps_satellite.py
tart/imaging/test/test_gps_time.py
tart/imaging/test/test_imaging.py
tart/imaging/test/test_location.py
tart/imaging/test/test_sun.py
tart/imaging/test/test_tart_util.py
tart/imaging/test/test_visibility.py
tart/operation/.gitignore
tart/operation/Makefile
tart/operation/README.md
tart/operation/__init__.py
tart/operation/observation.py
tart/operation/settings.py
tart/operation/test/__init__.py
tart/operation/test/all.py
tart/operation/test/test_observation.py
tart/operation/test/test_settings.py
tart/simulation/.gitignore
tart/simulation/Makefile
tart/simulation/README.md
tart/simulation/__init__.py
tart/simulation/antennas.py
tart/simulation/butter_filter.py
tart/simulation/calculate_delay.py
tart/simulation/radio.py
tart/simulation/sample_delay.py
tart/simulation/sample_size.py
tart/simulation/simulation_source.py
tart/simulation/simulator.py
tart/simulation/skymodel.py
tart/simulation/spectrum.py
tart/simulation/telescope_signals.py
tart/simulation/telescope_system.py
tart/simulation/test_observation.pkl
tart/simulation/util.py
tart/simulation/test/__init__.py
tart/simulation/test/all.py
tart-1.4.5.dist-info/METADATA
tart-1.4.5.dist-info/WHEEL
tart-1.4.5.dist-info/licenses/LICENSE.txt
tart-1.4.5.dist-info/RECORD
