Metadata-Version: 2.4
Name: tart
Version: 1.4.5
Summary: Transient Array Radio Telescope Imaging and Operation Library
Project-URL: Homepage, http://github.com/tmolteno/tart_modules
Author-email: Tim Molteno <tim@elec.ac.nz>
License-Expression: GPL-3.0-or-later
License-File: LICENSE.txt
Classifier: Development Status :: 4 - Beta
Classifier: Intended Audience :: Science/Research
Classifier: License :: OSI Approved :: GNU General Public License v3 (GPLv3)
Classifier: Programming Language :: Python :: 3
Classifier: Topic :: Communications :: Ham Radio
Classifier: Topic :: Scientific/Engineering
Requires-Python: >=3.11
Requires-Dist: h5py
Requires-Dist: numpy>=2.0.0
Requires-Dist: python-dateutil
Requires-Dist: scipy; extra != 'minimal'
Provides-Extra: all
Requires-Dist: jsonrpclib; extra == 'all'
Requires-Dist: matplotlib; extra == 'all'
Requires-Dist: pyfftw; extra == 'all'
Requires-Dist: requests; extra == 'all'
Requires-Dist: scipy; extra == 'all'
Provides-Extra: minimal
Provides-Extra: plotting
Requires-Dist: matplotlib; extra == 'plotting'
